vsts/__init__.py
vsts/_file_cache.py
vsts/credentials.py
vsts/exceptions.py
vsts/version.py
vsts/vss_client.py
vsts/vss_client_configuration.py
vsts/vss_connection.py
vsts/build/__init__.py
vsts/build/v4_0/__init__.py
vsts/build/v4_0/build_client.py
vsts/build/v4_0/models/__init__.py
vsts/build/v4_0/models/agent_pool_queue.py
vsts/build/v4_0/models/artifact_resource.py
vsts/build/v4_0/models/build.py
vsts/build/v4_0/models/build_artifact.py
vsts/build/v4_0/models/build_badge.py
vsts/build/v4_0/models/build_controller.py
vsts/build/v4_0/models/build_definition.py
vsts/build/v4_0/models/build_definition3_2.py
vsts/build/v4_0/models/build_definition_reference.py
vsts/build/v4_0/models/build_definition_revision.py
vsts/build/v4_0/models/build_definition_step.py
vsts/build/v4_0/models/build_definition_template.py
vsts/build/v4_0/models/build_definition_template3_2.py
vsts/build/v4_0/models/build_definition_variable.py
vsts/build/v4_0/models/build_log.py
vsts/build/v4_0/models/build_log_reference.py
vsts/build/v4_0/models/build_metric.py
vsts/build/v4_0/models/build_option.py
vsts/build/v4_0/models/build_option_definition.py
vsts/build/v4_0/models/build_option_definition_reference.py
vsts/build/v4_0/models/build_option_group_definition.py
vsts/build/v4_0/models/build_option_input_definition.py
vsts/build/v4_0/models/build_process.py
vsts/build/v4_0/models/build_report_metadata.py
vsts/build/v4_0/models/build_repository.py
vsts/build/v4_0/models/build_request_validation_result.py
vsts/build/v4_0/models/build_resource_usage.py
vsts/build/v4_0/models/build_settings.py
vsts/build/v4_0/models/build_trigger.py
vsts/build/v4_0/models/change.py
vsts/build/v4_0/models/data_source_binding_base.py
vsts/build/v4_0/models/definition_reference.py
vsts/build/v4_0/models/deployment.py
vsts/build/v4_0/models/folder.py
vsts/build/v4_0/models/identity_ref.py
vsts/build/v4_0/models/issue.py
vsts/build/v4_0/models/json_patch_operation.py
vsts-0.1.0b2.dist-info/DESCRIPTION.rst
vsts-0.1.0b2.dist-info/METADATA
vsts-0.1.0b2.dist-info/RECORD
vsts-0.1.0b2.dist-info/WHEEL
vsts-0.1.0b2.dist-info/metadata.json
vsts-0.1.0b2.dist-info/top_level.txt
