Metadata-Version: 2.0
Name: vsts
Version: 0.1.0b2
Summary: Python wrapper around the VSTS APIs
Home-page: https://github.com/Microsoft/vsts-python-api
Author: Microsoft Corporation
Author-email: vstscli@microsoft.com
License: MIT
Keywords: Microsoft,VSTS,Team Services,SDK,AzureTfs
Platform: UNKNOWN
Classifier: Development Status :: 4 - Beta
Classifier: Intended Audience :: Developers
Classifier: Intended Audience :: System Administrators
Classifier: Programming Language :: Python
Classifier: Programming Language :: Python :: 2
Classifier: Programming Language :: Python :: 2.7
Classifier: Programming Language :: Python :: 3
Classifier: Programming Language :: Python :: 3.6
Classifier: License :: OSI Approved :: MIT License
Requires-Dist: msrest (>=0.4.5)
